faknow/__init__.py
faknow/data/__init__.py
faknow/data/dataset/__init__.py
faknow/data/dataset/bigcn_dataset.py
faknow/data/dataset/cafe_dataset.py
faknow/data/dataset/dataset.py
faknow/data/dataset/dudef_dataset.py
faknow/data/dataset/fang_dataset.py
faknow/data/dataset/m3fend_dataset.py
faknow/data/dataset/multi_modal.py
faknow/data/dataset/safe_dataset.py
faknow/data/dataset/spotfake_dataset.py
faknow/data/dataset/text.py
faknow/data/dataset/trustrd_dataset.py
faknow/data/process/__init__.py
faknow/data/process/process.py
faknow/data/process/text_process.py
faknow/evaluate/__init__.py
faknow/evaluate/evaluator.py
faknow/evaluate/metrics.py
faknow/model/__init__.py
faknow/model/model.py
faknow/model/content_based/__init__.py
faknow/model/content_based/endef.py
faknow/model/content_based/m3fend.py
faknow/model/content_based/mdfend.py
faknow/model/content_based/textcnn.py
faknow/model/content_based/multi_modal/__init__.py
faknow/model/content_based/multi_modal/cafe.py
faknow/model/content_based/multi_modal/eann.py
faknow/model/content_based/multi_modal/hmcan.py
faknow/model/content_based/multi_modal/mcan.py
faknow/model/content_based/multi_modal/mfan.py
faknow/model/content_based/multi_modal/safe.py
faknow/model/content_based/multi_modal/spotfake.py
faknow/model/layers/__init__.py
faknow/model/layers/dct.py
faknow/model/layers/layer.py
faknow/model/layers/layers_m3fend.py
faknow/model/layers/transformer.py
faknow/model/social_context/__init__.py
faknow/model/social_context/base_gnn.py
faknow/model/social_context/bigcn.py
faknow/model/social_context/dudef.py
faknow/model/social_context/ebgcn.py
faknow/model/social_context/eddfn.py
faknow/model/social_context/fang.py
faknow/model/social_context/gcnfn.py
faknow/model/social_context/gnncl.py
faknow/model/social_context/trustrd.py
faknow/model/social_context/upfd.py
faknow/properties/bigcn.yaml
faknow/properties/config.yaml
faknow/properties/eann.yaml
faknow/properties/eddfn.yaml
faknow/properties/endef.yaml
faknow-0.0.3.dist-info/LICENSE
faknow-0.0.3.dist-info/METADATA
faknow-0.0.3.dist-info/WHEEL
faknow-0.0.3.dist-info/top_level.txt
faknow-0.0.3.dist-info/RECORD
